llogpy/llogpy.py
llogpy/test.py
llogpy-3.0.0.dist-info/LICENSE
llogpy-3.0.0.dist-info/METADATA
llogpy-3.0.0.dist-info/WHEEL
llogpy-3.0.0.dist-info/top_level.txt
llogpy-3.0.0.dist-info/RECORD
